Workbook

Sheet README
A1: ShadowFox Data Analyst Internship - Intermediate Level
A2: Intern: Rudra Kumar | SF-PID: SF-PID-2026-W6251 | Amrita Vishwa Vidyapeetham, Nagercoil
A4: Project: Customer and Revenue Analysis (Jan-Dec 2025)
A5: DATA NOTE: This is a SAMPLE dataset created for this exercise. It is not real company data.
A6: Currency is Indian Rupees (INR).
A8: Sheets
A9: Dashboard - KPIs and charts
A10: Insights - findings, reasons and recommendations
A11: Raw_Data - data before cleaning
A12: Cleaning_Log - each cleaning step and rows affected
A13: Clean_Data - cleaned order lines. Revenue and Profit are formulas.
A14: Customers - one row per customer, sorted by revenue (high to low), built with formulas
... A22: Top 10% share = revenue of the top 10% of customers / total revenue

Sheet Dashboard
A1: Customer and Revenue Dashboard - 2025 (Sample Data)
A3: Total Revenue (INR) | D3: Total Profit (INR) | G3: Profit Margin | J3: Total Orders
A4: =Analysis!C16 -> 20571768 | D4: =Analysis!D16 -> 6248167.5 | G4: =Analysis!D16/Analysis!C16 -> 0.30372536 | J4: =Analysis!E16 -> 2085
A6: Customers | D6: Repeat Rate | G6: Top 10% Customers Share | J6: Avg Order Value (INR)
A7: =Analysis!P4 -> 799 | D7: =Analysis!P6 -> 0.58197747 | G7: =Analysis!P10 -> 0.42432013 | J7: =Analysis!P14 -> 9866.5552

Sheet Insights
A1: Key Insights, Possible Reasons and Recommendations (sample dataset)
A3: What the data shows
A4: 1. Revenue is INR 205.72 lakh from 2085 orders and 799 customers. Profit is INR 62.48 lakh, a margin of 30.4%.
A5: 2. 58.2% of customers ordered more than once (465 customers). They bring 88.3% of revenue.
A6: 3. 41.8% of customers ordered only once. They are the largest single group but bring only 11.7% of revenue.
A7: 4. Revenue is concentrated. The top 10% of customers give 42.4% of revenue. The top 20% give 62.3%. The bottom 50% give only 10.2%.
A8: 5. Corporate customers spend most per customer (INR 0.87 lakh), against INR 0.14 lakh for Consumer and INR 0.25 lakh for Small Business.
A9: 6. Seasonality: Dec is the best month (INR 20.97 lakh) and Jul is the weakest (INR 12.37 lakh). Oct to Dec give 28.7% of yearly revenue.
A10: 7. Margins differ by category: Electronics 27.8%, Furniture 28.5%, Stationery 48.7%. South is the top region with 33.3% of revenue.
A12: Possible reasons
A13: - Corporate buyers order larger quantities, so a small group lifts revenue per customer.
A14: - November and December are strong months. Extra Q4 discounts may help volume.
... A26: All figures come from the Analysis sheet. The data is a sample, so use the results for practice only.

Sheet Raw_Data
A1: OrderID | B1: CustomerID | C1: Date | D1: Region | E1: Segment | F1: Category | G1: Product | H1: Qty | I1: UnitPrice | J1: Discount | K1: UnitCost
A2: ORD5001 | B2: C0001 | C2: 45719 | D2: North | E2: Consumer | F2: Stationery | G2: Planner | H2: 3 | I2: 600 | J2: 0 | K2: 300
A3: ORD5002 | B3: C0002 | C3: 45998 | D3: North | E3: Small Business | F3: Electronics | G3: Headphones | H3: 5 | I3: 2500 | J3: 0.15 | K3: 1600
A4: ORD5003 | B4: C0002 | C4: 45696 | D4: North | E4: Small Business | F4: Furniture | G4: Office Chair | H4: 4 | I4: 7000 | J4: 0 | K4: 4800
A5: ORD5004 | B5: C0003 | C5: 45995 | D5: South | E5: Consumer | F5: Stationery | G5: Notebook Set | H5: 6 | I5: 400 | J5: 0.15 | K5: 200
A6: ORD5005 | B6: C0004 | C6: 45943 | D6: East | E6: Small Business | F6: Stationery | G6: Pen Pack | H6: 6 | I6: 250 | J6: 0.15 | K6: 100
A7: ORD5006 | B7: C0004 | C7: 45910 | D7: East | E7: Small Business | F7: Furniture | G7: Office Chair | H7: 1 | I7: 7000 | J7: 0 | K7: 4800
A8: ORD5007 | B8: C0004 | C8: 46001 | D8: East | E8: Small Business | F8: Furniture | G8: Desk Lamp | H8: 5 | I8: 1200 | J8: 0.15 | K8: 600
A9: ORD5008 | B9: C0004 | C9: 45881 | D9: East | E9: Small Business | F9: Furniture | G9: Study Desk | H9: 5 | I9: 9000 | J9: 0 | K9: 6200
A10: ORD5009 | B10: C0004 | C10: 45920 | D10: East | E10: Small Business | F10: Stationery | G10: Notebook Set | H10: 7 | I10: 400 | J10: 0 | K10: 200
A11: ORD5010 | B11: C0005 | C11: 45823 | D11: West | E11: Corporate | F11: Furniture | G11: Study Desk | H11: 5 | I11: 9000 | J11: 0.1 | K11: 6200
A12: ORD5011 | B12: C0005 | C12: 45953 | E12: Corporate | F12: Furniture | G12: Desk Lamp | H12: 3 | I12: 1200 | J12: 0.1 | K12: 600
A13: ORD5012 | B13: C0005 | C13: 45727 | D13: West | E13: Corporate | F13: Furniture | G13: Study Desk | H13: 4 | I13: 9000 | J13: 0.15 | K13: 6200
A14: ORD5013 | B14: C0006 | C14: 45917 | D14: North | E14: Consumer | F14: Electronics | G14: Bluetooth Speaker | H14: 2 | I14: 3000 | J14: 0 | K14: 2000
A15: ORD5014 | B15: C0007 | C15: 45671 | D15: West | E15: Consumer | F15: Furniture | G15: Desk Lamp | H15: 1 | I15: 1200 | J15: 0.05 | K15: 600
A16: ORD5015 | B16: C0008 | C16: 46010 | D16: East | E16: Consumer | F16: Furniture | G16: Office Chair | H16: 3 | I16: 7000 | J16: 0.15 | K16: 4800
A17: ORD5016 | B17: C0009 | C17: 46010 | D17: East | E17: Consumer | F17: Furniture | G17: Bookshelf | H17: 2 | I17: 5500 | J17: 0.1 | K17: 3600
A18: ORD5017 | B18: C0010 | C18: 45977 | D18: North | E18: Consumer | F18: Stationery | G18: Marker Set | H18: 2 | I18: 500 | J18: 0.05 | K18: 250
A19: ORD5018 | B19: C0010 | C19: 45922 | D19: North | E19: Consumer | F19: Stationery | G19: Notebook Set | H19: 2 | I19: 400 | J19: 0.1 | K19: 200
A20: ORD5019 | B20: C0010 | C20: 45931 | D20: North | E20: Consumer | F20: Furniture | G20: Desk Lamp | H20: 2 | I20: 1200 | J20: 0.05 | K20: 600
A21: ORD5020 | B21: C0010 | C21: 46007 | D21: North | E21: Consumer | F21: Stationery | G21: Marker Set | H21: 4 | I21: 500 | J21: 0.05 | K21: 250
A22: ORD5021 | B22: C0010 | C22: 45974 | D22: North | E22: Consumer | F22: Electronics | G22: Headphones | H22: 1 | I22: 2500 | J22: 0.05 | K22: 1600
A23: ORD5022 | B23: C0011 | C23: 45884 | D23: North | E23: Small Business | F23: Stationery | G23: Marker Set | H23: 20 | I23: 500 | J23: 0 | K23: 250
A24: ORD5023 | B24: C0011 | C24: 45958 | D24: North | E24: Small Business | F24: Electronics | G24: Bluetooth Speaker | H24: 3 | I24: 3000 | J24: 0.1 | K24: 2000
... A178: ORD5177 | B178: C0064 | C178: 45871 | D178: South | E178: Consumer | F178: Furniture | G178: Desk Lamp | H178: 1 | I178: 1200 | J178: 0.05 | K178: 600
A179: ORD5178 | C179: 45878 | D179: South | E179: Consumer | F179: Electronics | G179: Bluetooth Speaker | H179: 1 | I179: 3000 | J179: 0 | K179: 2000
A180: ORD5179 | B180: C0065 | C180: 46003 | D180: South | E180: Consumer | F180: Furniture | G180: Study Desk | H180: 3 | I180: 9000 | J180: 0.05 | K180: 6200
A181: ORD5180 | B181: C0066 | C181: 46015 | D181: North | E181: Consumer | F181: Electronics | G181: Power Bank | H181: 2 | I181: 1500 | J181: 0.05 | K181: 900
A182: ORD5181 | B182: C0066 | C182: 45683 | D182: North | E182: Consumer | F182: Stationery | G182: Planner | H182: 4 | I182: 600 | J182: 0.1 | K182: 300
A183: ORD5182 | B183: C0066 | C183: 45984 | D183: North | E183: Consumer | F183: Electronics | G183: Headphones | H183: 1 | I183: 2500 | J183: 0.1 | K183: 1600
A184: ORD5183 | B184: C0066 | C184: 45752 | D184: North | E184: Consumer | F184: Electronics | G184: Bluetooth Speaker | H184: 2 | I184: 3000 | J184: 0.05 | K184: 2000
A185: ORD5184 | B185: C0066 | C185: 45957 | D185: North | E185: Consumer | F185: Electronics | G185: Bluetooth Speaker | H185: 1 | I185: 3000 | J185: 0.05 | K185: 2000
A186: ORD5185 | B186: C0066 | C186: 45976 | D186: North | E186: Consumer | F186: Stationery | G186: Pen Pack | H186: 6 | I186: 250 | J186: 0.05 | K186: 100
A187: ORD5186 | B187: C0067 | C187: 45851 | D187: East | E187: Corporate | F187: Furniture | G187: Bookshelf | H187: 6 | I187: 5500 | J187: 0.05 | K187: 3600
A188: ORD5187 | B188: C0067 | C188: 45854 | D188: South | E188: Corporate | F188: Furniture | G188: Study Desk | H188: 2 | I188: 9000 | J188: 0 | K188: 6200
A189: ORD5188 | B189: C0067 | C189: 45939 | D189: East | E189: Corporate | F189: Furniture | G189: Bookshelf | H189: 2 | I189: 5500 | J189: 0.05 | K189: 3600
A190: ORD5189 | B190: C0067 | C190: 45711 | D190: East | E190: Corporate | F190: Electronics | G190: Headphones | H190: 5 | I190: 2500 | J190: 0.15 | K190: 1600
A191: ORD5190 | B191: C0068 | C191: 45762 | D191: West | E191: Corporate | F191: Furniture | G191: Desk Lamp | H191: 3 | I191: 1200 | J191: 0.15 | K191: 600
... A215: ORD5214 | B215: C0072 | C215: 45950 | D215: South | E215: Consumer | F215: Stationery | G215: Pen Pack | H215: 7 | I215: 250 | J215: 0.15 | K215: 100
A216: ORD5215 | B216: C0072 | C216: 45940 | E216: Consumer | F216: Stationery | G216: Planner | H216: 7 | I216: 600 | J216: 0.05 | K216: 300
A217: ORD5216 | B217: C0072 | C217: 45760 | D217: South | E217: Consumer | F217: Furniture | G217: Study Desk | H217: 3 | I217: 9000 | J217: 0 | K217: 6200
A218: ORD5217 | B218: C0072 | C218: 45977 | D218: South | E218: Consumer | F218: Electronics | G218: Bluetooth Speaker | H218: 1 | I218: 3000 | J218: 0.05 | K218: 2000
A219: ORD5218 | B219: C0073 | C219: 45994 | D219: West | E219: Consumer | F219: Electronics | G219: Power Bank | H219: 1 | I219: 1500 | J219: 0.1 | K219: 900
A220: ORD5219 | B220: C0074 | C220: 45981 | D220: South | E220: Consumer | F220: Electronics | G220: Smart Watch | H220: 3 | I220: 4500 | J220: 0.1 | K220: 3300
A221: ORD5220 | B221: C0074 | C221: 45993 | D221: South | E221: Consumer | F221: Furniture | G221: Study Desk | H221: 2 | I221: 9000 | J221: 0.05 | K221: 6200
A222: ORD5221 | B222: C0074 | C222: 45904 | D222: South | E222: Consumer | F222: Stationery | G222: Marker Set | H222: 6 | I222: 500 | J222: 0 | K222: 250
A223: ORD5222 | B223: C0074 | C223: 45684 | D223: South | E223: Consumer | F223: Furniture | G223: Study Desk | H223: 1 | I223: 9000 | J223: 0.1 | K223: 6200
A224: ORD5223 | C224: 45981 | D224: South | E224: Consumer | F224: Furniture | G224: Office Chair | H224: 3 | I224: 7000 | J224: 0.1 | K224: 4800
A225: ORD5224 | B225: C0075 | C225: 45667 | D225: North | E225: Small Business | F225: Stationery | G225: Marker Set | H225: 14 | I225: 500 | J225: 0.05 | K225: 250
A226: ORD5225 | B226: C0076 | C226: 45945 | D226: South | E226: Consumer | F226: Stationery | G226: Pen Pack | H226: 5 | I226: 250 | J226: 0.05 | K226: 100
A227: ORD5226 | B227: C0076 | C227: 45793 | D227: South | E227: Consumer | F227: Electronics | G227: Bluetooth Speaker | H227: 1 | I227: 3000 | J227: 0.1 | K227: 2000
A228: ORD5227 | C228: 45713 | D228: South | E228: Consumer | F228: Furniture | G228: Desk Lamp | H228: 1 | I228: 1200 | J228: 0.1 | K228: 600
A229: ORD5228 | B229: C0077 | C229: 45719 | D229: East | E229: Consumer | F229: Electronics | G229: Bluetooth Speaker | H229: 1 | I229: 3000 | J229: 0 | K229: 2000
A230: ORD5229 | B230: C0077 | C230: 45714 | D230: East | E230: Consumer | F230: Electronics | G230: Smart Watch | H230: 2 | I230: 4500 | J230: 0 | K230: 3300
A231: ORD5230 | B231: C0077 | C231: 45993 | D231: East | E231: Consumer | F231: Furniture | G231: Desk Lamp | H231: 3 | I231: 1200 | J231: 0.05 | K231: 600
A232: ORD5231 | B232: C0077 | C232: 45691 | D232: East | E232: Consumer | F232: Stationery | G232: Pen Pack | H232: 2 | I232: 250 | J232: 0.1 | K232: 100
A233: ORD5232 | B233: C0077 | C233: 45717 | D233: East | E233: Consumer | F233: Furniture | G233: Office Chair | H233: 3 | I233: 7000 | J233: 0 | K233: 4800
A234: ORD5233 | B234: C0078 | C234: 45977 | D234: West | E234: Consumer | F234: Furniture | G234: Office Chair | H234: 3 | I234: 7000 | J234: 0.05 | K234: 4800
A235: ORD5234 | B235: C0079 | C235: 45994 | D235: South | E235: Consumer | F235: Stationery | G235: Planner | H235: 8 | I235: 600 | J235: 0.05 | K235: 300
A236: ORD5235 | B236: C0079 | C236: 45828 | D236: South | E236: Consumer | F236: Furniture | G236: Bookshelf | H236: 3 | I236: 5500 | J236: 0 | K236: 3600
A237: ORD5236 | B237: C0079 | C237: 45855 | D237: South | E237: Consumer | F237: Stationery | G237: Planner | H237: 8 | I237: 600 | J237: 0 | K237: 300
A238: ORD5237 | B238: C0079 | C238: 45705 | D238: South | E238: Consumer | F238: Electronics | G238: Bluetooth Speaker | H238: 1 | I238: 3000 | J238: 0.1 | K238: 2000
A239: ORD5238 | B239: C0080 | C239: 45814 | D239: South | E239: Consumer | F239: Stationery | G239: Pen Pack | H239: 4 | I239: 250 | J239: 0 | K239: 100
A240: ORD5239 | B240: C0080 | C240: 45974 | D240: South | E240: Consumer | F240: Stationery | G240: Marker Set | H240: 3 | I240: 500 | J240: 0.05 | K240: 250
... A315: ORD5314 | B315: C0114 | C315: 45873 | D315: East | E315: Small Business | F315: Electronics | G315: Smart Watch | H315: 2 | I315: 4500 | J315: 0 | K315: 3300
A316: ORD5315 | B316: C0114 | C316: 45978 | D316: East | E316: Small Business | F316: Furniture | G316: Desk Lamp | I316: 1200 | J316: 0.1 | K316: 600
A317: ORD5316 | B317: C0115 | C317: 45822 | D317: EAST | E317: Small Business | F317: Stationery | G317: Notebook Set | H317: 16 | I317: 400 | J317: 0 | K317: 200
A318: ORD5317 | B318: C0115 | C318: 45772 | D318: North | E318: Small Business | F318: Electronics | G318: Bluetooth Speaker | H318: 2 | I318: 3000 | J318: 0.1 | K318: 2000
A319: ORD5318 | B319: C0115 | C319: 45939 | D319: North | E319: Small Business | F319: Electronics | G319: Headphones | H319: 5 | I319: 2500 | J319: 0.05 | K319: 1600
A320: ORD5319 | B320: C0115 | C320: 45811 | D320: North | E320: Small Business | F320: Electronics | G320: Power Bank | H320: 4 | I320: 1500 | J320: 0 | K320: 900
A321: ORD5320 | B321: C0116 | C321: 45965 | D321: South | E321: Corporate | F321: Furniture | G321: Desk Lamp | H321: 6 | I321: 1200 | J321: 0.15 | K321: 600
A322: ORD5321 | B322: C0116 | C322: 46017 | D322: South | E322: Corporate | F322: Stationery | G322: Pen Pack | H322: 40 | I322: 250 | J322: 0.1 | K322: 100
A323: ORD5322 | B323: C0116 | C323: 45863 | D323: South | E323: Corporate | F323: Furniture | G323: Desk Lamp | H323: 3 | I323: 1200 | J323: 0.05 | K323: 600
A324: ORD5323 | B324: C0116 | C324: 45684 | D324: South | E324: Corporate | F324: Electronics | G324: Headphones | H324: 5 | I324: 2500 | J324: 0.05 | K324: 1600
A325: ORD5324 | B325: C0117 | C325: 45802 | D325: north | E325: Consumer | F325: Furniture | G325: Study Desk | H325: 2 | I325: 9000 | J325: 0 | K325: 6200
A326: ORD5325 | B326: C0117 | C326: 45970 | D326: East | E326: Consumer | F326: Stationery | G326: Pen Pack | H326: 8 | I326: 250 | J326: 0.05 | K326: 100
A327: ORD5326 | B327: C0117 | C327: 45977 | D327: East | E327: Consumer | F327: Furniture | G327: Desk Lamp | H327: 3 | I327: 1200 | J327: 0.05 | K327: 600
A328: ORD5327 | B328: C0118 | C328: 45798 | D328: South | E328: Consumer | F328: Electronics | G328: Headphones | H328: 3 | I328: 2500 | J328: 0 | K328: 1600
... A333: ORD5332 | B333: C0121 | C333: 45756 | D333: South | E333: Consumer | F333: Electronics | G333: Headphones | H333: 1 | I333: 2500 | J333: 0 | K333: 1600
A334: ORD5333 | B334: C0121 | C334: 45906 | D334: South | E334: Consumer | F334: Furniture | G334: Office Chair | I334: 7000 | J334: 0 | K334: 4800
A335: ORD5334 | B335: C0121 | C335: 45803 | D335: South | E335: Consumer | F335: Furniture | G335: Desk Lamp | H335: 2 | I335: 1200 | J335: 0.05 | K335: 600
A336: ORD5335 | B336: C0122 | C336: 45710 | D336: South | E336: Consumer | F336: Electronics | G336: Smart Watch | H336: 3 | I336: 4500 | J336: 0 | K336: 3300
A337: ORD5336 | B337: C0123 | C337: 46008 | D337: South | E337: Consumer | F337: Stationery | G337: Planner | H337: 3 | I337: 600 | J337: 0.05 | K337: 300
A338: ORD5337 | B338: C0124 | C338: 45948 | D338: South | E338: Small Business | F338: Electronics | G338: Headphones | H338: 4 | I338: 2500 | J338: 0.05 | K338: 1600
A339: ORD5338 | B339: C0125 | C339: 45793 | D339: South | E339: Small Business | F339: Stationery | G339: Notebook Set | H339: 18 | I339: 400 | J339: 0 | K339: 200
A340: ORD5339 | B340: C0125 | C340: 45662 | D340: South | E340: Small Business | F340: Electronics | G340: Bluetooth Speaker | H340: 1 | I340: 3000 | J340: 0.05 | K340: 2000
A341: ORD5340 | B341: C0126 | C341: 45797 | D341: East | E341: Consumer | F341: Stationery | G341: Marker Set | H341: 3 | I341: 500 | J341: 0.1 | K341: 250
A342: ORD5341 | B342: C0127 | C342: 45916 | D342: East | E342: Consumer | F342: Stationery | G342: Notebook Set | H342: 3 | I342: 400 | J342: 0.1 | K342: 200
A343: ORD5342 | B343: C0127 | C343: 46013 | D343: East | E343: Consumer | F343: Electronics | G343: Power Bank | H343: 2 | I343: 1500 | J343: 0.1 | K343: 900
A344: ORD5343 | B344: C0127 | C344: 45870 | D344: South | E344: Consumer | F344: Stationery | G344: Notebook Set | H344: 3 | I344: 400 | J344: 0 | K344: 200
A345: ORD5344 | B345: C0128 | C345: 45978 | D345: South | E345: Small Business | F345: Stationery | G345: Notebook Set | H345: 15 | I345: 400 | J345: 0.05 | K345: 200
A346: ORD5345 | B346: C0128 | C346: 46014 | D346: South | E346: Small Business | F346: Furniture | G346: Desk Lamp | H346: 2 | I346: 1200 | J346: 0.05 | K346: 600
... A436: ORD5435 | B436: C0170 | C436: 45986 | D436: North | E436: Consumer | F436: Electronics | G436: Headphones | H436: 2 | I436: 2500 | J436: 0.05 | K436: 1600
A437: ORD5436 | B437: C0170 | C437: 45801 | E437: Consumer | F437: Stationery | G437: Marker Set | H437: 6 | I437: 500 | J437: 0 | K437: 250
A438: ORD5437 | B438: C0171 | C438: 45966 | D438: West | E438: Consumer | F438: Stationery | G438: Marker Set | H438: 5 | I438: 500 | J438: 0.15 | K438: 250
A439: ORD5438 | B439: C0171 | C439: 45783 | D439: West | E439: Consumer | F439: Stationery | G439: Notebook Set | H439: 3 | I439: 400 | J439: 0.1 | K439: 200
A440: ORD5439 | B440: C0172 | C440: 45927 | D440: West | E440: Consumer | F440: Stationery | G440: Pen Pack | H440: 2 | I440: 250 | J440: 0.1 | K440: 100
A441: ORD5440 | B441: C0173 | C441: 45939 | D441: East | E441: Corporate | F441: Furniture | G441: Office Chair | H441: 7 | I441: 7000 | J441: 0.1 | K441: 4800
A442: ORD5441 | B442: C0173 | C442: 45770 | D442: East | E442: Corporate | F442: Stationery | G442: Notebook Set | H442: 26 | I442: 400 | J442: 0.05 | K442: 200
A443: ORD5442 | B443: C0173 | C443: 45861 | D443: East | E443: Corporate | F443: Furniture | G443: Desk Lamp | H443: 8 | I443: 1200 | J443: 0 | K443: 600
...

Sheet Cleaning_Log
A1: Step | B1: Action | C1: Rows affected
A2: Start | B2: Rows in raw data | C2: 2132
A3: 1 | B3: Removed exact duplicate rows | C3: 20
A4: 2 | B4: Trimmed spaces and fixed text case in Region | C4: 26
A5: 3 | B5: Missing Region labelled "Unspecified" (rows kept) | C5: 10
A6: 4 | B6: Removed rows with missing CustomerID (cannot be used for customer analysis) | C6: 15
A7: 5 | B7: Removed rows with missing Qty (revenue cannot be calculated) | C7: 12
A8: End | B8: Rows in clean data | C8: 2085

Sheet Clean_Data
A1: OrderID | B1: CustomerID | C1: Date | D1: Month | E1: Region | F1: Segment | G1: Category | H1: Product | I1: Qty | J1: UnitPrice | K1: Discount | L1: UnitCost | M1: Revenue | N1: Profit
A2: ORD5260 | B2: C0094 | C2: 45658 | D2: =MONTH(C2) -> 1 | E2: South | F2: Small Business | G2: Electronics | H2: Headphones | I2: 4 | J2: 2500 | K2: 0.1 | L2: 1600 | M2: =I2*J2*(1-K2) -> 9000 | N2: =M2-I2*L2 -> 2600
A3: ORD5836 | B3: C0320 | C3: 45658 | D3: =MONTH(C3) -> 1 | E3: South | F3: Small Business | G3: Stationery | H3: Pen Pack | I3: 5 | J3: 250 | K3: 0 | L3: 100 | M3: =I3*J3*(1-K3) -> 1250 | N3: =M3-I3*L3 -> 750
A4: ORD5843 | B4: C0323 | C4: 45658 | D4: =MONTH(C4) -> 1 | E4: East | F4: Consumer | G4: Furniture | H4: Study Desk | I4: 2 | J4: 9000 | K4: 0.1 | L4: 6200 | M4: =I4*J4*(1-K4) -> 16200 | N4: =M4-I4*L4 -> 3800
A5: ORD6044 | B5: C0401 | C5: 45658 | D5: =MONTH(C5) -> 1 | E5: East | F5: Small Business | G5: Electronics | H5: Power Bank | I5: 1 | J5: 1500 | K5: 0.1 | L5: 900 | M5: =I5*J5*(1-K5) -> 1350 | N5: =M5-I5*L5 -> 450
A6: ORD6339 | B6: C0496 | C6: 45658 | D6: =MONTH(C6) -> 1 | E6: South | F6: Corporate | G6: Furniture | H6: Desk Lamp | I6: 5 | J6: 1200 | K6: 0 | L6: 600 | M6: =I6*J6*(1-K6) -> 6000 | N6: =M6-I6*L6 -> 3000
A7: ORD5592 | B7: C0233 | C7: 45659 | D7: =MONTH(C7) -> 1 | E7: West | F7: Small Business | G7: Furniture | H7: Desk Lamp | I7: 2 | J7: 1200 | K7: 0.1 | L7: 600 | M7: =I7*J7*(1-K7) -> 2160 | N7: =M7-I7*L7 -> 960
A8: ORD5733 | B8: C0279 | C8: 45659 | D8: =MONTH(C8) -> 1 | E8: East | F8: Consumer | G8: Furniture | H8: Office Chair | I8: 2 | J8: 7000 | K8: 0 | L8: 4800 | M8: =I8*J8*(1-K8) -> 14000 | N8: =M8-I8*L8 -> 4400
A9: ORD6342 | B9: C0497 | C9: 45659 | D9: =MONTH(C9) -> 1 | E9: West | F9: Consumer | G9: Electronics | H9: Power Bank | I9: 2 | J9: 1500 | K9: 0.05 | L9: 900 | M9: =I9*J9*(1-K9) -> 2850 | N9: =M9-I9*L9 -> 1050
A10: ORD6463 | B10: C0540 | C10: 45659 | D10: =MONTH(C10) -> 1 | E10: South | F10: Small Business | G10: Stationery | H10: Planner | I10: 15 | J10: 600 | K10: 0 | L10: 300 | M10: =I10*J10*(1-K10) -> 9000 | N10: =M10-I10*L10 -> 4500
A11: ORD6593 | B11: C0598 | C11: 45659 | D11: =MONTH(C11) -> 1 | E11: South | F11: Consumer | G11: Stationery | H11: Marker Set | I11: 2 | J11: 500 | K11: 0.1 | L11: 250 | M11: =I11*J11*(1-K11) -> 900 | N11: =M11-I11*L11 -> 400
A12: ORD6900 | B12: C0717 | C12: 45659 | D12: =MONTH(C12) -> 1 | E12: South | F12: Small Business | G12: Stationery | H12: Notebook Set | I12: 5 | J12: 400 | K12: 0 | L12: 200 | M12: =I12*J12*(1-K12) -> 2000 | N12: =M12-I12*L12 -> 1000
A13: ORD7093 | B13: C0794 | C13: 45659 | D13: =MONTH(C13) -> 1 | E13: North | F13: Consumer | G13: Electronics | H13: Smart Watch | I13: 2 | J13: 4500 | K13: 0 | L13: 3300 | M13: =I13*J13*(1-K13) -> 9000 | N13: =M13-I13*L13 -> 2400
... A2086: ORD6276 | B2086: C0480 | C2086: 46019 | D2086: =MONTH(C2086) -> 12 | E2086: North | F2086: Consumer | G2086: Electronics | H2086: Smart Watch | I2086: 1 | J2086: 4500 | K2086: 0.05 | L2086: 3300 | M2086: =I2086*J2086*(1-K2086) -> 4275 | N2086: =M2086-I2086*L2086 -> 975

Sheet Customers
A1: CustomerID | B1: Segment | C1: Orders | D1: Revenue | E1: Profit | F1: Type | G1: Cumulative Share
A2: C0347 | B2: =INDEX(Clean_Data!$F$2:$F$2086,MATCH(A2,Clean_Data!$B$2:$B$2086,0)) -> Corporate | C2: =COUNTIFS(Clean_Data!$B$2:$B$2086,A2) -> 9 | D2: =SUMIFS(Clean_Data!$M$2:$M$2086,Clean_Data!$B$2:$B$2086,A2) -> 280930 | E2: =SUMIFS(Clean_Data!$N$2:$N$2086,Clean_Data!$B$2:$B$2086,A2) -> 75930 | F2: =IF(C2>1,"Repeat","One-time") -> Repeat | G2: =SUM($D$2:D2)/SUM($D$2:$D$800) -> 0.013656094
A3: C0133 | B3: =INDEX(Clean_Data!$F$2:$F$2086,MATCH(A3,Clean_Data!$B$2:$B$2086,0)) -> Corporate | C3: =COUNTIFS(Clean_Data!$B$2:$B$2086,A3) -> 11 | D3: =SUMIFS(Clean_Data!$M$2:$M$2086,Clean_Data!$B$2:$B$2086,A3) -> 276420 | E3: =SUMIFS(Clean_Data!$N$2:$N$2086,Clean_Data!$B$2:$B$2086,A3) -> 78920 | F3: =IF(C3>1,"Repeat","One-time") -> Repeat | G3: =SUM($D$2:D3)/SUM($D$2:$D$800) -> 0.027092956
A4: C0432 | B4: =INDEX(Clean_Data!$F$2:$F$2086,MATCH(A4,Clean_Data!$B$2:$B$2086,0)) -> Corporate | C4: =COUNTIFS(Clean_Data!$B$2:$B$2086,A4) -> 13 | D4: =SUMIFS(Clean_Data!$M$2:$M$2086,Clean_Data!$B$2:$B$2086,A4) -> 244640 | E4: =SUMIFS(Clean_Data!$N$2:$N$2086,Clean_Data!$B$2:$B$2086,A4) -> 68240 | F4: =IF(C4>1,"Repeat","One-time") -> Repeat | G4: =SUM($D$2:D4)/SUM($D$2:$D$800) -> 0.038984983
A5: C0504 | B5: =INDEX(Clean_Data!$F$2:$F$2086,MATCH(A5,Clean_Data!$B$2:$B$2086,0)) -> Corporate | C5: =COUNTIFS(Clean_Data!$B$2:$B$2086,A5) -> 6 | D5: =SUMIFS(Clean_Data!$M$2:$M$2086,Clean_Data!$B$2:$B$2086,A5) -> 230300 | E5: =SUMIFS(Clean_Data!$N$2:$N$2086,Clean_Data!$B$2:$B$2086,A5) -> 61500 | F5: =IF(C5>1,"Repeat","One-time") -> Repeat | G5: =SUM($D$2:D5)/SUM($D$2:$D$800) -> 0.050179937
A6: C0025 | B6: =INDEX(Clean_Data!$F$2:$F$2086,MATCH(A6,Clean_Data!$B$2:$B$2086,0)) -> Corporate | C6: =COUNTIFS(Clean_Data!$B$2:$B$2086,A6) -> 8 | D6: =SUMIFS(Clean_Data!$M$2:$M$2086,Clean_Data!$B$2:$B$2086,A6) -> 224650 | E6: =SUMIFS(Clean_Data!$N$2:$N$2086,Clean_Data!$B$2:$B$2086,A6) -> 59650 | F6: =IF(C6>1,"Repeat","One-time") -> Repeat | G6: =SUM($D$2:D6)/SUM($D$2:$D$800) -> 0.061100243
A7: C0400 | B7: =INDEX(Clean_Data!$F$2:$F$2086,MATCH(A7,Clean_Data!$B$2:$B$2086,0)) -> Corporate | C7: =COUNTIFS(Clean_Data!$B$2:$B$2086,A7) -> 5 | D7: =SUMIFS(Clean_Data!$M$2:$M$2086,Clean_Data!$B$2:$B$2086,A7) -> 209825 | E7: =SUMIFS(Clean_Data!$N$2:$N$2086,Clean_Data!$B$2:$B$2086,A7) -> 59925 | F7: =IF(C7>1,"Repeat","One-time") -> Repeat | G7: =SUM($D$2:D7)/SUM($D$2:$D$800) -> 0.071299902
A8: C0225 | B8: =INDEX(Clean_Data!$F$2:$F$2086,MATCH(A8,Clean_Data!$B$2:$B$2086,0)) -> Corporate | C8: =COUNTIFS(Clean_Data!$B$2:$B$2086,A8) -> 5 | D8: =SUMIFS(Clean_Data!$M$2:$M$2086,Clean_Data!$B$2:$B$2086,A8) -> 184650 | E8: =SUMIFS(Clean_Data!$N$2:$N$2086,Clean_Data!$B$2:$B$2086,A8) -> 41850 | F8: =IF(C8>1,"Repeat","One-time") -> Repeat | G8: =SUM($D$2:D8)/SUM($D$2:$D$800) -> 0.080275795
A9: C0216 | B9: =INDEX(Clean_Data!$F$2:$F$2086,MATCH(A9,Clean_Data!$B$2:$B$2086,0)) -> Corporate | C9: =COUNTIFS(Clean_Data!$B$2:$B$2086,A9) -> 8 | D9: =SUMIFS(Clean_Data!$M$2:$M$2086,Clean_Data!$B$2:$B$2086,A9) -> 179875 | E9: =SUMIFS(Clean_Data!$N$2:$N$2086,Clean_Data!$B$2:$B$2086,A9) -> 46175 | F9: =IF(C9>1,"Repeat","One-time") -> Repeat | G9: =SUM($D$2:D9)/SUM($D$2:$D$800) -> 0.089019575
A10: C0798 | B10: =INDEX(Clean_Data!$F$2:$F$2086,MATCH(A10,Clean_Data!$B$2:$B$2086,0)) -> Corporate | C10: =COUNTIFS(Clean_Data!$B$2:$B$2086,A10) -> 5 | D10: =SUMIFS(Clean_Data!$M$2:$M$2086,Clean_Data!$B$2:$B$2086,A10) -> 178700 | E10: =SUMIFS(Clean_Data!$N$2:$N$2086,Clean_Data!$B$2:$B$2086,A10) -> 47500 | F10: =IF(C10>1,"Repeat","One-time") -> Repeat | G10: =SUM($D$2:D10)/SUM($D$2:$D$800) -> 0.097706237
A11: C0422 | B11: =INDEX(Clean_Data!$F$2:$F$2086,MATCH(A11,Clean_Data!$B$2:$B$2086,0)) -> Corporate | C11: =COUNTIFS(Clean_Data!$B$2:$B$2086,A11) -> 11 | D11: =SUMIFS(Clean_Data!$M$2:$M$2086,Clean_Data!$B$2:$B$2086,A11) -> 174880 | E11: =SUMIFS(Clean_Data!$N$2:$N$2086,Clean_Data!$B$2:$B$2086,A11) -> 44880 | F11: =IF(C11>1,"Repeat","One-time") -> Repeat | G11: =SUM($D$2:D11)/SUM($D$2:$D$800) -> 0.10620721
A12: C0622 | B12: =INDEX(Clean_Data!$F$2:$F$2086,MATCH(A12,Clean_Data!$B$2:$B$2086,0)) -> Corporate | C12: =COUNTIFS(Clean_Data!$B$2:$B$2086,A12) -> 7 | D12: =SUMIFS(Clean_Data!$M$2:$M$2086,Clean_Data!$B$2:$B$2086,A12) -> 160415 | E12: =SUMIFS(Clean_Data!$N$2:$N$2086,Clean_Data!$B$2:$B$2086,A12) -> 44415 | F12: =IF(C12>1,"Repeat","One-time") -> Repeat | G12: =SUM($D$2:D12)/SUM($D$2:$D$800) -> 0.11400503
A13: C0482 | B13: =INDEX(Clean_Data!$F$2:$F$2086,MATCH(A13,Clean_Data!$B$2:$B$2086,0)) -> Corporate | C13: =COUNTIFS(Clean_Data!$B$2:$B$2086,A13) -> 8 | D13: =SUMIFS(Clean_Data!$M$2:$M$2086,Clean_Data!$B$2:$B$2086,A13) -> 159150 | E13: =SUMIFS(Clean_Data!$N$2:$N$2086,Clean_Data!$B$2:$B$2086,A13) -> 47350 | F13: =IF(C13>1,"Repeat","One-time") -> Repeat | G13: =SUM($D$2:D13)/SUM($D$2:$D$800) -> 0.12174136
... A800: C0245 | B800: =INDEX(Clean_Data!$F$2:$F$2086,MATCH(A800,Clean_Data!$B$2:$B$2086,0)) -> Consumer | C800: =COUNTIFS(Clean_Data!$B$2:$B$2086,A800) -> 1 | D800: =SUMIFS(Clean_Data!$M$2:$M$2086,Clean_Data!$B$2:$B$2086,A800) -> 425 | E800: =SUMIFS(Clean_Data!$N$2:$N$2086,Clean_Data!$B$2:$B$2086,A800) -> 225 | F800: =IF(C800>1,"Repeat","One-time") -> One-time | G800: =SUM($D$2:D800)/SUM($D$2:$D$800) -> 1

Sheet Analysis
A1: Summary tables (all values calculated from Clean_Data and Customers)
A3: Month No | B3: Month | C3: Revenue | D3: Profit | E3: Orders | F3: MoM Growth | G3: Seasonality Index | I3: Orders per customer | J3: Customers | K3: Share of Customers | L3: Revenue | M3: Share of Revenue | O3: Customer KPI | P3: Value
A4: 1 | B4: Jan | C4: =SUMIFS(Clean_Data!$M$2:$M$2086,Clean_Data!$D$2:$D$2086,A4) -> 1484130 | D4: =SUMIFS(Clean_Data!$N$2:$N$2086,Clean_Data!$D$2:$D$2086,A4) -> 472880 | E4: =COUNTIFS(Clean_Data!$D$2:$D$2086,A4) -> 147 | G4: =C4/AVERAGE($C$4:$C$15) -> 0.86572824 | I4: 1 order | J4: =COUNTIFS(Customers!$C$2:$C$800,1) -> 334 | K4: =J4/$J$9 -> 0.41802253 | L4: =SUMIFS(Customers!$D$2:$D$800,Customers!$C$2:$C$800,1) -> 2413890 | M4: =L4/$L$9 -> 0.11733994 | O4: Total customers | P4: =COUNTA(Customers!$A$2:$A$800) -> 799
A5: 2 | B5: Feb | C5: =SUMIFS(Clean_Data!$M$2:$M$2086,Clean_Data!$D$2:$D$2086,A5) -> 1500235 | D5: =SUMIFS(Clean_Data!$N$2:$N$2086,Clean_Data!$D$2:$D$2086,A5) -> 466735 | E5: =COUNTIFS(Clean_Data!$D$2:$D$2086,A5) -> 157 | F5: =IF(C4=0,0,C5/C4-1) -> 0.010851475 | G5: =C5/AVERAGE($C$4:$C$15) -> 0.87512267 | I5: 2 orders | J5: =COUNTIFS(Customers!$C$2:$C$800,2) -> 169 | K5: =J5/$J$9 -> 0.21151439 | L5: =SUMIFS(Customers!$D$2:$D$800,Customers!$C$2:$C$800,2) -> 2913377.5 | M5: =L5/$L$9 -> 0.14162018 | O5: Repeat customers | P5: =COUNTIF(Customers!$F$2:$F$800,"Repeat") -> 465
A6: 3 | B6: Mar | C6: =SUMIFS(Clean_Data!$M$2:$M$2086,Clean_Data!$D$2:$D$2086,A6) -> 1587085 | D6: =SUMIFS(Clean_Data!$N$2:$N$2086,Clean_Data!$D$2:$D$2086,A6) -> 505435 | E6: =COUNTIFS(Clean_Data!$D$2:$D$2086,A6) -> 153 | F6: =IF(C5=0,0,C6/C5-1) -> 0.05789093 | G6: =C6/AVERAGE($C$4:$C$15) -> 0.92578433 | I6: 3 orders | J6: =COUNTIFS(Customers!$C$2:$C$800,3) -> 109 | K6: =J6/$J$9 -> 0.13642053 | L6: =SUMIFS(Customers!$D$2:$D$800,Customers!$C$2:$C$800,3) -> 3469285 | M6: =L6/$L$9 -> 0.16864302 | O6: Repeat rate | P6: =P5/P4 -> 0.58197747
A7: 4 | B7: Apr | C7: =SUMIFS(Clean_Data!$M$2:$M$2086,Clean_Data!$D$2:$D$2086,A7) -> 1742470 | D7: =SUMIFS(Clean_Data!$N$2:$N$2086,Clean_Data!$D$2:$D$2086,A7) -> 540320 | E7: =COUNTIFS(Clean_Data!$D$2:$D$2086,A7) -> 159 | F7: =IF(C6=0,0,C7/C6-1) -> 0.097905909 | G7: =C7/AVERAGE($C$4:$C$15) -> 1.0164241 | I7: 4-5 orders | J7: =COUNTIFS(Customers!$C$2:$C$800,">=4",Customers!$C$2:$C$800,"<=5") -> 114 | K7: =J7/$J$9 -> 0.14267835 | L7: =SUMIFS(Customers!$D$2:$D$800,Customers!$C$2:$C$800,">=4",Customers!$C$2:$C$800,"<=5") -> 5933232.5 | M7: =L7/$L$9 -> 0.28841627 | O7: Revenue from repeat customers | P7: =SUMIFS(Customers!$D$2:$D$800,Customers!$F$2:$F$800,"Repeat") -> 18157878
A8: 5 | B8: May | C8: =SUMIFS(Clean_Data!$M$2:$M$2086,Clean_Data!$D$2:$D$2086,A8) -> 2009810 | D8: =SUMIFS(Clean_Data!$N$2:$N$2086,Clean_Data!$D$2:$D$2086,A8) -> 629460 | E8: =COUNTIFS(Clean_Data!$D$2:$D$2086,A8) -> 177 | F8: =IF(C7=0,0,C8/C7-1) -> 0.15342588 | G8: =C8/AVERAGE($C$4:$C$15) -> 1.1723699 | I8: 6+ orders | J8: =COUNTIFS(Customers!$C$2:$C$800,">=6") -> 73 | K8: =J8/$J$9 -> 0.091364205 | L8: =SUMIFS(Customers!$D$2:$D$800,Customers!$C$2:$C$800,">=6") -> 5841982.5 | M8: =L8/$L$9 -> 0.28398058 | O8: Repeat revenue share | P8: =P7/Analysis!C16 -> 0.88266006
A9: 6 | B9: Jun | C9: =SUMIFS(Clean_Data!$M$2:$M$2086,Clean_Data!$D$2:$D$2086,A9) -> 1484227.5 | D9: =SUMIFS(Clean_Data!$N$2:$N$2086,Clean_Data!$D$2:$D$2086,A9) -> 439777.5 | E9: =COUNTIFS(Clean_Data!$D$2:$D$2086,A9) -> 154 | F9: =IF(C8=0,0,C9/C8-1) -> -0.26150855 | G9: =C9/AVERAGE($C$4:$C$15) -> 0.86578511 | I9: Total | J9: =SUM(J4:J8) -> 799 | K9: =SUM(K4:K8) -> 1 | L9: =SUM(L4:L8) -> 20571768 | M9: =SUM(M4:M8) -> 1 | O9: Top 10% customers revenue | P9: =SUM(Customers!$D$2:$D$81) -> 8729015
A10: 7 | B10: Jul | C10: =SUMIFS(Clean_Data!$M$2:$M$2086,Clean_Data!$D$2:$D$2086,A10) -> 1237125 | D10: =SUMIFS(Clean_Data!$N$2:$N$2086,Clean_Data!$D$2:$D$2086,A10) -> 389325 | E10: =COUNTIFS(Clean_Data!$D$2:$D$2086,A10) -> 128 | F10: =IF(C9=0,0,C10/C9-1) -> -0.1664856 | G10: =C10/AVERAGE($C$4:$C$15) -> 0.72164436 | O10: Top 10% share | P10: =P9/Analysis!C16 -> 0.42432013
A11: 8 | B11: Aug | C11: =SUMIFS(Clean_Data!$M$2:$M$2086,Clean_Data!$D$2:$D$2086,A11) -> 1856082.5 | D11: =SUMIFS(Clean_Data!$N$2:$N$2086,Clean_Data!$D$2:$D$2086,A11) -> 551032.5 | E11: =COUNTIFS(Clean_Data!$D$2:$D$2086,A11) -> 154 | F11: =IF(C10=0,0,C11/C10-1) -> 0.50031929 | G11: =C11/AVERAGE($C$4:$C$15) -> 1.082697 | O11: Top 20% customers revenue | P11: =SUM(Customers!$D$2:$D$161) -> 12806742
A12: 9 | B12: Sep | C12: =SUMIFS(Clean_Data!$M$2:$M$2086,Clean_Data!$D$2:$D$2086,A12) -> 1774650 | D12: =SUMIFS(Clean_Data!$N$2:$N$2086,Clean_Data!$D$2:$D$2086,A12) -> 562350 | E12: =COUNTIFS(Clean_Data!$D$2:$D$2086,A12) -> 182 | F12: =IF(C11=0,0,C12/C11-1) -> -0.043873319 | G12: =C12/AVERAGE($C$4:$C$15) -> 1.0351954 | I12: Customer Decile | J12: Customers | K12: Revenue | L12: Share of Revenue | O12: Top 20% share | P12: =P11/Analysis!C16 -> 0.62253973
A13: 10 | B13: Oct | C13: =SUMIFS(Clean_Data!$M$2:$M$2086,Clean_Data!$D$2:$D$2086,A13) -> 1724992.5 | D13: =SUMIFS(Clean_Data!$N$2:$N$2086,Clean_Data!$D$2:$D$2086,A13) -> 478242.5 | E13: =COUNTIFS(Clean_Data!$D$2:$D$2086,A13) -> 198 | F13: =IF(C12=0,0,C13/C12-1) -> -0.027981574 | G13: =C13/AVERAGE($C$4:$C$15) -> 1.006229 | I13: Decile 1 | J13: =ROWS(Customers!$D$2:$D$81) -> 80 | K13: =SUM(Customers!$D$2:$D$81) -> 8729015 | L13: =K13/$K$23 -> 0.42432013 | O13: Revenue per customer | P13: =Analysis!C16/P4 -> 25746.893
A14: 11 | B14: Nov | C14: =SUMIFS(Clean_Data!$M$2:$M$2086,Clean_Data!$D$2:$D$2086,A14) -> 2073995 | D14: =SUMIFS(Clean_Data!$N$2:$N$2086,Clean_Data!$D$2:$D$2086,A14) -> 618895 | E14: =COUNTIFS(Clean_Data!$D$2:$D$2086,A14) -> 262 | F14: =IF(C13=0,0,C14/C13-1) -> 0.20232117 | G14: =C14/AVERAGE($C$4:$C$15) -> 1.2098105 | I14: Decile 2 | J14: =ROWS(Customers!$D$82:$D$161) -> 80 | K14: =SUM(Customers!$D$82:$D$161) -> 4077727.5 | L14: =K14/$K$23 -> 0.1982196 | O14: Average order value | P14: =Analysis!C16/Analysis!E16 -> 9866.5552
A15: 12 | B15: Dec | C15: =SUMIFS(Clean_Data!$M$2:$M$2086,Clean_Data!$D$2:$D$2086,A15) -> 2096965 | D15: =SUMIFS(Clean_Data!$N$2:$N$2086,Clean_Data!$D$2:$D$2086,A15) -> 593715 | E15: =COUNTIFS(Clean_Data!$D$2:$D$2086,A15) -> 214 | F15: =IF(C14=0,0,C15/C14-1) -> 0.011075244 | G15: =C15/AVERAGE($C$4:$C$15) -> 1.2232094 | I15: Decile 3 | J15: =ROWS(Customers!$D$162:$D$241) -> 80 | K15: =SUM(Customers!$D$162:$D$241) -> 2618492.5 | L15: =K15/$K$23 -> 0.12728573
B16: Total | C16: =SUM(C4:C15) -> 20571768 | D16: =SUM(D4:D15) -> 6248167.5 | E16: =SUM(E4:E15) -> 2085 | I16: Decile 4 | J16: =ROWS(Customers!$D$242:$D$321) -> 80 | K16: =SUM(Customers!$D$242:$D$321) -> 1818160 | L16: =K16/$K$23 -> 0.088381322
I17: Decile 5 | J17: =ROWS(Customers!$D$322:$D$401) -> 80 | K17: =SUM(Customers!$D$322:$D$401) -> 1249615 | L17: =K17/$K$23 -> 0.060744173
I18: Decile 6 | J18: =ROWS(Customers!$D$402:$D$481) -> 80 | K18: =SUM(Customers!$D$402:$D$481) -> 808775 | L18: =K18/$K$23 -> 0.039314804
I19: Decile 7 | J19: =ROWS(Customers!$D$482:$D$561) -> 80 | K19: =SUM(Customers!$D$482:$D$561) -> 558697.5 | L19: =K19/$K$23 -> 0.027158459
I20: Decile 8 | J20: =ROWS(Customers!$D$562:$D$641) -> 80 | K20: =SUM(Customers!$D$562:$D$641) -> 359550 | L20: =K20/$K$23 -> 0.017477837
I21: Decile 9 | J21: =ROWS(Customers!$D$642:$D$721) -> 80 | K21: =SUM(Customers!$D$642:$D$721) -> 232615 | L21: =K21/$K$23 -> 0.011307487
I22: Decile 10 | J22: =ROWS(Customers!$D$722:$D$800) -> 79 | K22: =SUM(Customers!$D$722:$D$800) -> 119120 | L22: =K22/$K$23 -> 0.0057904602
I23: Total | J23: =SUM(J13:J22) -> 799 | K23: =SUM(K13:K22) -> 20571768 | L23: =SUM(L13:L22) -> 1
I24: Decile 1 = top 10% of customers by revenue
A27: Segment | B27: Customers | C27: Orders | D27: Revenue | E27: Profit | F27: Margin | G27: Revenue per Customer | H27: Avg Order Value
A28: Consumer | B28: =COUNTIFS(Customers!$B$2:$B$800,A28) -> 486 | C28: =COUNTIFS(Clean_Data!$F$2:$F$2086,A28) -> 1194 | D28: =SUMIFS(Clean_Data!$M$2:$M$2086,Clean_Data!$F$2:$F$2086,A28) -> 6629660 | E28: =SUMIFS(Clean_Data!$N$2:$N$2086,Clean_Data!$F$2:$F$2086,A28) -> 2136860 | F28: =E28/D28 -> 0.32231819 | G28: =D28/B28 -> 13641.276 | H28: =D28/C28 -> 5552.4791
A29: Small Business | B29: =COUNTIFS(Customers!$B$2:$B$800,A29) -> 214 | C29: =COUNTIFS(Clean_Data!$F$2:$F$2086,A29) -> 474 | D29: =SUMIFS(Clean_Data!$M$2:$M$2086,Clean_Data!$F$2:$F$2086,A29) -> 5374527.5 | E29: =SUMIFS(Clean_Data!$N$2:$N$2086,Clean_Data!$F$2:$F$2086,A29) -> 1732027.5 | F29: =E29/D29 -> 0.322266 | G29: =D29/B29 -> 25114.614 | H29: =D29/C29 -> 11338.666
A30: Corporate | B30: =COUNTIFS(Customers!$B$2:$B$800,A30) -> 99 | C30: =COUNTIFS(Clean_Data!$F$2:$F$2086,A30) -> 417 | D30: =SUMIFS(Clean_Data!$M$2:$M$2086,Clean_Data!$F$2:$F$2086,A30) -> 8567580 | E30: =SUMIFS(Clean_Data!$N$2:$N$2086,Clean_Data!$F$2:$F$2086,A30) -> 2379280 | F30: =E30/D30 -> 0.27770736 | G30: =D30/B30 -> 86541.212 | H30: =D30/C30 -> 20545.755
A31: Total | B31: =SUM(B28:B30) -> 799 | C31: =SUM(C28:C30) -> 2085 | D31: =SUM(D28:D30) -> 20571768 | E31: =SUM(E28:E30) -> 6248167.5 | F31: =E31/D31 -> 0.30372536 | G31: =D31/B31 -> 25746.893 | H31: =D31/C31 -> 9866.5552
A34: Category | B34: Revenue | C34: Profit | D34: Margin | E34: Share of Revenue
A35: Electronics | B35: =SUMIFS(Clean_Data!$M$2:$M$2086,Clean_Data!$G$2:$G$2086,A35) -> 5209825 | C35: =SUMIFS(Clean_Data!$N$2:$N$2086,Clean_Data!$G$2:$G$2086,A35) -> 1448125 | D35: =C35/B35 -> 0.27796039 | E35: =B35/$B$38 -> 0.25325121
A36: Furniture | B36: =SUMIFS(Clean_Data!$M$2:$M$2086,Clean_Data!$G$2:$G$2086,A36) -> 13243540 | C36: =SUMIFS(Clean_Data!$N$2:$N$2086,Clean_Data!$G$2:$G$2086,A36) -> 3768740 | D36: =C36/B36 -> 0.28457195 | E36: =B36/$B$38 -> 0.64377259
A37: Stationery | B37: =SUMIFS(Clean_Data!$M$2:$M$2086,Clean_Data!$G$2:$G$2086,A37) -> 2118402.5 | C37: =SUMIFS(Clean_Data!$N$2:$N$2086,Clean_Data!$G$2:$G$2086,A37) -> 1031302.5 | D37: =C37/B37 -> 0.48683029 | E37: =B37/$B$38 -> 0.1029762
A38: Total | B38: =SUM(B35:B37) -> 20571768 | C38: =SUM(C35:C37) -> 6248167.5 | D38: =C38/B38 -> 0.30372536 | E38: =SUM(E35:E37) -> 1
A41: Region | B41: Revenue | C41: Profit | D41: Orders | E41: Share of Revenue
A42: North | B42: =SUMIFS(Clean_Data!$M$2:$M$2086,Clean_Data!$E$2:$E$2086,A42) -> 5301452.5 | C42: =SUMIFS(Clean_Data!$N$2:$N$2086,Clean_Data!$E$2:$E$2086,A42) -> 1631502.5 | D42: =COUNTIFS(Clean_Data!$E$2:$E$2086,A42) -> 560 | E42: =B42/$B$47 -> 0.25770525
A43: South | B43: =SUMIFS(Clean_Data!$M$2:$M$2086,Clean_Data!$E$2:$E$2086,A43) -> 6853002.5 | C43: =SUMIFS(Clean_Data!$N$2:$N$2086,Clean_Data!$E$2:$E$2086,A43) -> 2095152.5 | D43: =COUNTIFS(Clean_Data!$E$2:$E$2086,A43) -> 719 | E43: =B43/$B$47 -> 0.33312658
A44: East | B44: =SUMIFS(Clean_Data!$M$2:$M$2086,Clean_Data!$E$2:$E$2086,A44) -> 4380590 | C44: =SUMIFS(Clean_Data!$N$2:$N$2086,Clean_Data!$E$2:$E$2086,A44) -> 1312040 | D44: =COUNTIFS(Clean_Data!$E$2:$E$2086,A44) -> 403 | E44: =B44/$B$47 -> 0.21294184
A45: West | B45: =SUMIFS(Clean_Data!$M$2:$M$2086,Clean_Data!$E$2:$E$2086,A45) -> 3901537.5 | C45: =SUMIFS(Clean_Data!$N$2:$N$2086,Clean_Data!$E$2:$E$2086,A45) -> 1169187.5 | D45: =COUNTIFS(Clean_Data!$E$2:$E$2086,A45) -> 393 | E45: =B45/$B$47 -> 0.18965495
A46: Unspecified | B46: =SUMIFS(Clean_Data!$M$2:$M$2086,Clean_Data!$E$2:$E$2086,A46) -> 135185 | C46: =SUMIFS(Clean_Data!$N$2:$N$2086,Clean_Data!$E$2:$E$2086,A46) -> 40285 | D46: =COUNTIFS(Clean_Data!$E$2:$E$2086,A46) -> 10 | E46: =B46/$B$47 -> 0.0065713848
A47: Total | B47: =SUM(B42:B46) -> 20571768 | C47: =SUM(C42:C46) -> 6248167.5 | D47: =SUM(D42:D46) -> 2085 | E47: =SUM(E42:E46) -> 1
