Workbook

Sheet Dashboard
A1: Retail Sales Dashboard - 2025 (Sample Data)
A3: Total Revenue (INR) | C3: Total Profit (INR) | E3: Profit Margin | G3: Total Orders | I3: Avg Order Value (INR) | K3: Units Sold
A4: =Analysis!C16 -> 4461267.5 | C4: =Analysis!D16 -> 1466317.5 | E4: =Analysis!D16/Analysis!C16 -> 0.32867733 | G4: =Analysis!E16 -> 684 | I4: =Analysis!C16/Analysis!E16 -> 6522.3209 | K4: =Analysis!F16 -> 2396
A6: Top Product (revenue) | C6: Top Category | E6: Top Region | G6: Best Month | I6: Weakest Month | K6: Lowest-margin Product
A7: =INDEX(Analysis!A20:A31,MATCH(MAX(Analysis!C20:C31),Analysis!C20:C31,0)) -> Study Desk | C7: =INDEX(Analysis!I4:I6,MATCH(MAX(Analysis!J4:J6),Analysis!J4:J6,0)) -> Furniture | E7: =INDEX(Analysis!I10:I13,MATCH(MAX(Analysis!J10:J13),Analysis!J10:J13,0)) -> South | G7: =INDEX(Analysis!B4:B15,MATCH(MAX(Analysis!C4:C15),Analysis!C4:C15,0)) -> Nov | I7: =INDEX(Analysis!B4:B15,MATCH(MIN(Analysis!C4:C15),Analysis!C4:C15,0)) -> Feb | K7: =INDEX(Analysis!A20:A31,MATCH(MIN(Analysis!F20:F31),Analysis!F20:F31,0)) -> Smart Watch

Sheet README
A1: ShadowFox Data Analyst Internship - Beginner Level
A2: Intern: Rudra Kumar | SF-PID: SF-PID-2026-W6251 | Amrita Vishwa Vidyapeetham, Nagercoil
A4: Project: Retail Sales Performance Dashboard (Jan-Dec 2025)
A5: DATA NOTE: This is a SAMPLE retail dataset created for this exercise. It is not real company data.
A6: Currency is Indian Rupees (INR).
A8: Sheets in this workbook
A9: Raw_Data - the data before cleaning
A10: Cleaning_Log - every cleaning step and how many rows it affected
A11: Clean_Data - the cleaned dataset. Revenue and Profit are formulas.
A12: Analysis - summary tables built with SUMIFS and COUNTIFS
A13: Dashboard - KPIs and charts
A14: Insights - findings and recommendations
... A19: Margin = Profit / Revenue

Sheet Raw_Data
A1: OrderID | B1: Date | C1: Region | D1: Category | E1: Product | F1: Qty | G1: UnitPrice | H1: Discount | I1: UnitCost
A2: ORD1001 | B2: 45665 | C2: North | D2: Stationery | E2: Planner | F2: 6 | G2: 600 | H2: 0 | I2: 300
A3: ORD1002 | B3: 45675 | C3: East | D3: Electronics | E3: Power Bank | F3: 3 | G3: 1500 | H3: 0.1 | I3: 900
A4: ORD1003 | B4: 45660 | C4: South | D4: Electronics | E4: Smart Watch | G4: 4500 | H4: 0 | I4: 3300
A5: ORD1004 | B5: 45675 | C5: North | D5: Electronics | E5: Bluetooth Speaker | F5: 3 | G5: 3000 | H5: 0 | I5: 2000
A6: ORD1005 | B6: 45671 | C6: East | D6: Electronics | E6: Bluetooth Speaker | F6: 3 | G6: 3000 | H6: 0.05 | I6: 2000
A7: ORD1006 | B7: 45682 | C7: South | D7: Electronics | E7: Bluetooth Speaker | F7: 2 | G7: 3000 | H7: 0 | I7: 2000
A8: ORD1007 | B8: 45662 | C8: East | D8: Electronics | E8: Power Bank | F8: 2 | G8: 1500 | H8: 0 | I8: 900
A9: ORD1008 | B9: 45660 | C9: West | D9: Electronics | E9: Bluetooth Speaker | F9: 2 | G9: 3000 | H9: 0 | I9: 2000
A10: ORD1009 | B10: 45666 | C10: North | D10: Furniture | E10: Bookshelf | F10: 2 | G10: 5500 | H10: 0.05 | I10: 3600
A11: ORD1010 | B11: 45670 | C11: East | D11: Electronics | E11: Headphones | F11: 3 | G11: 2500 | H11: 0 | I11: 1600
A12: ORD1011 | B12: 45685 | C12: South | D12: Electronics | E12: Smart Watch | F12: 3 | G12: 4500 | H12: 0.05 | I12: 3300
A13: ORD1012 | B13: 45659 | C13: South | D13: Furniture | E13: Study Desk | F13: 3 | G13: 9000 | H13: 0 | I13: 6200
A14: ORD1013 | B14: 45685 | C14: North | D14: Stationery | E14: Planner | F14: 6 | G14: 600 | H14: 0 | I14: 300
A15: ORD1014 | B15: 45672 | C15: West | D15: Electronics | E15: Bluetooth Speaker | F15: 2 | G15: 3000 | H15: 0 | I15: 2000
A16: ORD1015 | B16: 45669 | C16: West | D16: Stationery | E16: Planner | F16: 4 | G16: 600 | H16: 0 | I16: 300
... A65: ORD1064 | B65: 45716 | C65: North | D65: Stationery | E65: Notebook Set | F65: 10 | G65: 400 | H65: 0 | I65: 200
A66: ORD1065 | B66: 45716 | D66: Electronics | E66: Power Bank | F66: 1 | G66: 1500 | H66: 0.1 | I66: 900
A67: ORD1066 | B67: 45707 | C67: South | D67: Electronics | E67: Bluetooth Speaker | F67: 3 | G67: 3000 | H67: 0 | I67: 2000
A68: ORD1067 | B68: 45710 | C68: North | D68: Stationery | E68: Pen Pack | F68: 3 | G68: 250 | H68: 0 | I68: 100
A69: ORD1068 | B69: 45695 | C69: South | D69: Stationery | E69: Pen Pack | F69: 7 | G69: 250 | H69: 0 | I69: 100
A70: ORD1069 | B70: 45701 | C70: East | D70: Stationery | E70: Planner | F70: 5 | G70: 600 | H70: 0 | I70: 300
A71: ORD1070 | B71: 45699 | C71: East | D71: Electronics | E71: Power Bank | F71: 2 | G71: 1500 | H71: 0 | I71: 900
A72: ORD1071 | B72: 45692 | C72: North | D72: Electronics | E72: Smart Watch | F72: 3 | G72: 4500 | H72: 0.05 | I72: 3300
A73: ORD1072 | B73: 45693 | C73: South | D73: Electronics | E73: Smart Watch | F73: 3 | G73: 4500 | H73: 0 | I73: 3300
A74: ORD1073 | B74: 45698 | C74: West | D74: Furniture | E74: Study Desk | F74: 1 | G74: 9000 | H74: 0 | I74: 6200
A75: ORD1074 | B75: 45698 | C75: South | D75: Electronics | E75: Power Bank | F75: 3 | G75: 1500 | H75: 0.1 | I75: 900
A76: ORD1075 | B76: 45710 | C76: West | D76: Stationery | E76: Pen Pack | F76: 10 | G76: 250 | H76: 0 | I76: 100
A77: ORD1076 | B77: 45697 | C77: South | D77: Stationery | E77: Notebook Set | F77: 3 | G77: 400 | H77: 0 | I77: 200
A78: ORD1077 | B78: 45693 | C78: West | D78: Electronics | E78: Smart Watch | F78: 3 | G78: 4500 | H78: 0.05 | I78: 3300
... A96: ORD1095 | B96: 45701 | C96: North | D96: Electronics | E96: Bluetooth Speaker | F96: 3 | G96: 3000 | H96: 0 | I96: 2000
A97: ORD1096 | B97: 45700 | C97: South | D97: Furniture | E97: Study Desk | G97: 9000 | H97: 0 | I97: 6200
A98: ORD1097 | B98: 45689 | C98: South | D98: Stationery | E98: Planner | F98: 10 | G98: 600 | H98: 0 | I98: 300
A99: ORD1098 | B99: 45707 | C99: west | D99: Electronics | E99: Smart Watch | F99: 2 | G99: 4500 | H99: 0 | I99: 3300
A100: ORD1099 | B100: 45700 | C100: North | D100: Furniture | E100: Office Chair | F100: 3 | G100: 7000 | H100: 0 | I100: 4800
A101: ORD1100 | B101: 45733 | C101: East | D101: Stationery | E101: Marker Set | F101: 8 | G101: 500 | H101: 0.05 | I101: 250
A102: ORD1101 | B102: 45725 | C102: South | D102: Electronics | E102: Smart Watch | F102: 3 | G102: 4500 | H102: 0 | I102: 3300
A103: ORD1102 | B103: 45742 | C103: East | D103: Electronics | E103: Headphones | F103: 1 | G103: 2500 | H103: 0.05 | I103: 1600
A104: ORD1103 | B104: 45730 | C104: East | D104: Stationery | E104: Notebook Set | F104: 5 | G104: 400 | H104: 0 | I104: 200
A105: ORD1104 | B105: 45727 | C105: West | D105: Electronics | E105: Smart Watch | F105: 2 | G105: 4500 | H105: 0.05 | I105: 3300
A106: ORD1105 | B106: 45726 | C106: West | D106: Stationery | E106: Planner | F106: 6 | G106: 600 | H106: 0.05 | I106: 300
A107: ORD1106 | B107: 45726 | C107: South | D107: Stationery | E107: Planner | F107: 8 | G107: 600 | H107: 0.1 | I107: 300
A108: ORD1107 | B108: 45729 | C108: North | D108: Stationery | E108: Notebook Set | F108: 8 | G108: 400 | H108: 0.1 | I108: 200
A109: ORD1108 | B109: 45735 | C109: East | D109: Stationery | E109: Planner | F109: 4 | G109: 600 | H109: 0.05 | I109: 300
... A217: ORD1216 | B217: 45783 | C217: East | D217: Stationery | E217: Planner | F217: 5 | G217: 600 | H217: 0.1 | I217: 300
A218: ORD1217 | B218: 45780 | D218: Furniture | E218: Office Chair | F218: 3 | G218: 7000 | H218: 0 | I218: 4800
A219: ORD1218 | B219: 45781 | C219: West | D219: Electronics | E219: Bluetooth Speaker | F219: 1 | G219: 3000 | H219: 0 | I219: 2000
A220: ORD1219 | B220: 45787 | C220: West | D220: Stationery | E220: Planner | F220: 9 | G220: 600 | H220: 0.1 | I220: 300
A221: ORD1220 | B221: 45793 | C221: East | D221: Stationery | E221: Notebook Set | F221: 8 | G221: 400 | H221: 0 | I221: 200
A222: ORD1221 | B222: 45784 | C222: South | D222: Electronics | E222: Bluetooth Speaker | F222: 1 | G222: 3000 | H222: 0 | I222: 2000
A223: ORD1222 | B223: 45786 | C223: South | D223: Stationery | E223: Pen Pack | F223: 4 | G223: 250 | H223: 0 | I223: 100
A224: ORD1223 | B224: 45804 | C224: South | D224: Furniture | E224: Bookshelf | F224: 3 | G224: 5500 | H224: 0 | I224: 3600
A225: ORD1224 | B225: 45796 | D225: Electronics | E225: Headphones | F225: 2 | G225: 2500 | H225: 0.05 | I225: 1600
A226: ORD1225 | B226: 45795 | C226: South | D226: Stationery | E226: Planner | F226: 4 | G226: 600 | H226: 0 | I226: 300
A227: ORD1226 | B227: 45790 | C227: South | D227: Furniture | E227: Desk Lamp | F227: 3 | G227: 1200 | H227: 0.05 | I227: 600
A228: ORD1227 | B228: 45785 | C228: West | D228: Furniture | E228: Desk Lamp | F228: 1 | G228: 1200 | H228: 0.1 | I228: 600
A229: ORD1228 | B229: 45788 | C229: South | D229: Stationery | E229: Pen Pack | F229: 8 | G229: 250 | H229: 0 | I229: 100
A230: ORD1229 | B230: 45799 | C230: South | D230: Stationery | E230: Marker Set | F230: 8 | G230: 500 | H230: 0 | I230: 250
A231: ORD1230 | B231: 45782 | C231: West | D231: Stationery | E231: Planner | F231: 9 | G231: 600 | H231: 0 | I231: 300
A232: ORD1231 | B232: 45805 | C232: West | D232: Stationery | E232: Notebook Set | F232: 7 | G232: 400 | H232: 0 | I232: 200
A233: ORD1232 | B233: 45801 | C233: North | D233: Furniture | E233: Desk Lamp | F233: 2 | G233: 1200 | H233: 0 | I233: 600
A234: ORD1233 | B234: 45780 | C234: South | D234: Electronics | E234: Power Bank | F234: 3 | G234: 1500 | H234: 0 | I234: 900
A235: ORD1234 | B235: 45797 | C235: East | D235: Furniture | E235: Desk Lamp | F235: 2 | G235: 1200 | H235: 0 | I235: 600
A236: ORD1235 | B236: 45805 | C236: South | D236: Stationery | E236: Marker Set | F236: 3 | G236: 500 | H236: 0 | I236: 250
A237: ORD1236 | B237: 45798 | C237: West | D237: Stationery | E237: Planner | F237: 8 | G237: 600 | H237: 0 | I237: 300
... A336: ORD1335 | B336: 45852 | C336: South | D336: Stationery | E336: Pen Pack | F336: 7 | G336: 250 | H336: 0 | I336: 100
A337: ORD1336 | B337: 45855 | C337: North | D337: Electronics | E337: Smart Watch | G337: 4500 | H337: 0 | I337: 3300
A338: ORD1337 | B338: 45849 | C338: South | D338: Electronics | E338: Smart Watch | F338: 2 | G338: 4500 | H338: 0.1 | I338: 3300
A339: ORD1338 | B339: 45855 | C339: South | D339: Electronics | E339: Bluetooth Speaker | F339: 1 | G339: 3000 | H339: 0 | I339: 2000
A340: ORD1339 | B340: 45863 | C340: North | D340: Stationery | E340: Planner | F340: 10 | G340: 600 | H340: 0 | I340: 300
A341: ORD1340 | B341: 45846 | C341: South | D341: Furniture | E341: Study Desk | F341: 3 | G341: 9000 | H341: 0 | I341: 6200
A342: ORD1341 | B342: 45858 | C342: North | D342: Electronics | E342: Smart Watch | F342: 1 | G342: 4500 | H342: 0 | I342: 3300
A343: ORD1342 | B343: 45844 | C343: East | D343: Electronics | E343: Power Bank | F343: 3 | G343: 1500 | H343: 0 | I343: 900
A344: ORD1343 | B344: 45857 | C344: South | D344: Stationery | E344: Planner | F344: 9 | G344: 600 | H344: 0.1 | I344: 300
A345: ORD1344 | B345: 45849 | C345: East | D345: Stationery | E345: Planner | F345: 7 | G345: 600 | H345: 0.1 | I345: 300
A346: ORD1345 | B346: 45859 | C346: South | D346: Electronics | E346: Power Bank | F346: 2 | G346: 1500 | H346: 0 | I346: 900
A347: ORD1346 | B347: 45850 | C347: East | D347: Furniture | E347: Office Chair | F347: 3 | G347: 7000 | H347: 0 | I347: 4800
A348: ORD1347 | B348: 45840 | C348: North | D348: Stationery | E348: Notebook Set | F348: 9 | G348: 400 | H348: 0 | I348: 200
A349: ORD1348 | B349: 45859 | C349: South | D349: Electronics | E349: Headphones | F349: 2 | G349: 2500 | H349: 0 | I349: 1600
... A367: ORD1366 | B367: 45894 | C367: North | D367: Furniture | E367: Office Chair | F367: 1 | G367: 7000 | H367: 0 | I367: 4800
A368: ORD1367 | B368: 45872 | D368: Furniture | E368: Desk Lamp | F368: 1 | G368: 1200 | H368: 0 | I368: 600
A369: ORD1368 | B369: 45894 | C369: West | D369: Furniture | E369: Office Chair | F369: 1 | G369: 7000 | H369: 0.05 | I369: 4800
A370: ORD1369 | B370: 45891 | C370: West | D370: Stationery | E370: Notebook Set | F370: 10 | G370: 400 | H370: 0 | I370: 200
A371: ORD1370 | B371: 45889 | C371: West | D371: Furniture | E371: Study Desk | F371: 3 | G371: 9000 | H371: 0 | I371: 6200
A372: ORD1371 | B372: 45894 | C372: North | D372: Furniture | E372: Bookshelf | F372: 1 | G372: 5500 | H372: 0.1 | I372: 3600
A373: ORD1372 | B373: 45884 | C373: West | D373: Stationery | E373: Pen Pack | F373: 4 | G373: 250 | H373: 0.1 | I373: 100
A374: ORD1373 | B374: 45877 | C374: South | D374: Electronics | E374: Headphones | F374: 3 | G374: 2500 | H374: 0.1 | I374: 1600
A375: ORD1374 | B375: 45877 | C375: East | D375: Furniture | E375: Desk Lamp | F375: 3 | G375: 1200 | H375: 0 | I375: 600
A376: ORD1375 | B376: 45881 | C376: North | D376: Stationery | E376: Notebook Set | F376: 9 | G376: 400 | H376: 0 | I376: 200
A377: ORD1376 | B377: 45894 | C377: West | D377: Stationery | E377: Planner | F377: 9 | G377: 600 | H377: 0 | I377: 300
A378: ORD1377 | B378: 45883 | C378: East | D378: Furniture | E378: Office Chair | F378: 3 | G378: 7000 | H378: 0.05 | I378: 4800
A379: ORD1378 | B379: 45897 | C379: West | D379: Electronics | E379: Power Bank | F379: 3 | G379: 1500 | H379: 0 | I379: 900
A380: ORD1379 | B380: 45887 | C380: North | D380: Furniture | E380: Office Chair | F380: 2 | G380: 7000 | H380: 0 | I380: 4800
... A408: ORD1407 | B408: 45909 | C408: South | D408: Furniture | E408: Office Chair | F408: 3 | G408: 7000 | H408: 0 | I408: 4800
A409: ORD1408 | B409: 45912 | D409: Electronics | E409: Headphones | F409: 1 | G409: 2500 | H409: 0 | I409: 1600
A410: ORD1409 | B410: 45904 | C410: West | D410: Electronics | E410: Headphones | F410: 2 | G410: 2500 | H410: 0 | I410: 1600
A411: ORD1410 | B411: 45915 | C411: South | D411: Furniture | E411: Study Desk | F411: 2 | G411: 9000 | H411: 0.1 | I411: 6200
A412: ORD1411 | B412: 45923 | C412: South | D412: Furniture | E412: Bookshelf | F412: 1 | G412: 5500 | H412: 0 | I412: 3600
A413: ORD1412 | B413: 45926 | C413: South | D413: Furniture | E413: Desk Lamp | F413: 3 | G413: 1200 | H413: 0 | I413: 600
A414: ORD1413 | B414: 45920 | C414: East | D414: Electronics | E414: Smart Watch | F414: 1 | G414: 4500 | H414: 0 | I414: 3300
...

Sheet Cleaning_Log
A1: Step | B1: Action | C1: Rows affected
A2: Start | B2: Rows in raw data | C2: 707
A3: 1 | B3: Removed exact duplicate rows | C3: 15
A4: 2 | B4: Trimmed spaces and fixed text case in Region (e.g. north, " South", "EAST ") | C4: 12
A5: 3 | B5: Missing Region labelled "Unspecified" (rows kept, as sales data is still valid) | C5: 9
A6: 4 | B6: Removed rows with missing Qty (revenue cannot be calculated) | C6: 8
A7: End | B7: Rows in clean data | C7: 684

Sheet Clean_Data
A1: OrderID | B1: Date | C1: Month | D1: Region | E1: Category | F1: Product | G1: Qty | H1: UnitPrice | I1: Discount | J1: UnitCost | K1: Revenue | L1: Profit
A2: ORD1036 | B2: 45658 | C2: =MONTH(B2) -> 1 | D2: West | E2: Stationery | F2: Notebook Set | G2: 7 | H2: 400 | I2: 0 | J2: 200 | K2: =G2*H2*(1-I2) -> 2800 | L2: =K2-G2*J2 -> 1400
A3: ORD1046 | B3: 45659 | C3: =MONTH(B3) -> 1 | D3: East | E3: Stationery | F3: Marker Set | G3: 5 | H3: 500 | I3: 0 | J3: 250 | K3: =G3*H3*(1-I3) -> 2500 | L3: =K3-G3*J3 -> 1250
A4: ORD1012 | B4: 45659 | C4: =MONTH(B4) -> 1 | D4: South | E4: Furniture | F4: Study Desk | G4: 3 | H4: 9000 | I4: 0 | J4: 6200 | K4: =G4*H4*(1-I4) -> 27000 | L4: =K4-G4*J4 -> 8400
A5: ORD1037 | B5: 45659 | C5: =MONTH(B5) -> 1 | D5: West | E5: Electronics | F5: Smart Watch | G5: 2 | H5: 4500 | I5: 0 | J5: 3300 | K5: =G5*H5*(1-I5) -> 9000 | L5: =K5-G5*J5 -> 2400
A6: ORD1020 | B6: 45660 | C6: =MONTH(B6) -> 1 | D6: West | E6: Electronics | F6: Headphones | G6: 2 | H6: 2500 | I6: 0 | J6: 1600 | K6: =G6*H6*(1-I6) -> 5000 | L6: =K6-G6*J6 -> 1800
A7: ORD1045 | B7: 45660 | C7: =MONTH(B7) -> 1 | D7: North | E7: Stationery | F7: Notebook Set | G7: 5 | H7: 400 | I7: 0 | J7: 200 | K7: =G7*H7*(1-I7) -> 2000 | L7: =K7-G7*J7 -> 1000
A8: ORD1008 | B8: 45660 | C8: =MONTH(B8) -> 1 | D8: West | E8: Electronics | F8: Bluetooth Speaker | G8: 2 | H8: 3000 | I8: 0 | J8: 2000 | K8: =G8*H8*(1-I8) -> 6000 | L8: =K8-G8*J8 -> 2000
A9: ORD1027 | B9: 45660 | C9: =MONTH(B9) -> 1 | D9: East | E9: Electronics | F9: Power Bank | G9: 2 | H9: 1500 | I9: 0.05 | J9: 900 | K9: =G9*H9*(1-I9) -> 2850 | L9: =K9-G9*J9 -> 1050
A10: ORD1043 | B10: 45661 | C10: =MONTH(B10) -> 1 | D10: South | E10: Stationery | F10: Planner | G10: 10 | H10: 600 | I10: 0 | J10: 300 | K10: =G10*H10*(1-I10) -> 6000 | L10: =K10-G10*J10 -> 3000
A11: ORD1039 | B11: 45662 | C11: =MONTH(B11) -> 1 | D11: West | E11: Furniture | F11: Desk Lamp | G11: 3 | H11: 1200 | I11: 0 | J11: 600 | K11: =G11*H11*(1-I11) -> 3600 | L11: =K11-G11*J11 -> 1800
A12: ORD1007 | B12: 45662 | C12: =MONTH(B12) -> 1 | D12: East | E12: Electronics | F12: Power Bank | G12: 2 | H12: 1500 | I12: 0 | J12: 900 | K12: =G12*H12*(1-I12) -> 3000 | L12: =K12-G12*J12 -> 1200
A13: ORD1054 | B13: 45663 | C13: =MONTH(B13) -> 1 | D13: South | E13: Electronics | F13: Bluetooth Speaker | G13: 1 | H13: 3000 | I13: 0 | J13: 2000 | K13: =G13*H13*(1-I13) -> 3000 | L13: =K13-G13*J13 -> 1000
... A685: ORD1689 | B685: 46018 | C685: =MONTH(B685) -> 12 | D685: South | E685: Stationery | F685: Planner | G685: 4 | H685: 600 | I685: 0 | J685: 300 | K685: =G685*H685*(1-I685) -> 2400 | L685: =K685-G685*J685 -> 1200

Sheet Analysis
A1: Summary tables (all values calculated from Clean_Data)
A3: Month No | B3: Month | C3: Revenue | D3: Profit | E3: Orders | F3: Units | G3: MoM Growth | I3: Category | J3: Revenue | K3: Profit | L3: Margin | M3: Share of Revenue
A4: 1 | B4: Jan | C4: =SUMIFS(Clean_Data!$K$2:$K$685,Clean_Data!$C$2:$C$685,A4) -> 311505 | D4: =SUMIFS(Clean_Data!$L$2:$L$685,Clean_Data!$C$2:$C$685,A4) -> 107955 | E4: =COUNTIFS(Clean_Data!$C$2:$C$685,A4) -> 54 | F4: =SUMIFS(Clean_Data!$G$2:$G$685,Clean_Data!$C$2:$C$685,A4) -> 197 | I4: Electronics | J4: =SUMIFS(Clean_Data!$K$2:$K$685,Clean_Data!$E$2:$E$685,I4) -> 1319700 | K4: =SUMIFS(Clean_Data!$L$2:$L$685,Clean_Data!$E$2:$E$685,I4) -> 386900 | L4: =IF(J4=0,0,K4/J4) -> 0.29317269 | M4: =J4/$J$7 -> 0.29581279
A5: 2 | B5: Feb | C5: =SUMIFS(Clean_Data!$K$2:$K$685,Clean_Data!$C$2:$C$685,A5) -> 262205 | D5: =SUMIFS(Clean_Data!$L$2:$L$685,Clean_Data!$C$2:$C$685,A5) -> 87655 | E5: =COUNTIFS(Clean_Data!$C$2:$C$685,A5) -> 43 | F5: =SUMIFS(Clean_Data!$G$2:$G$685,Clean_Data!$C$2:$C$685,A5) -> 152 | G5: =IF(C4=0,0,C5/C4-1) -> -0.15826391 | I5: Furniture | J5: =SUMIFS(Clean_Data!$K$2:$K$685,Clean_Data!$E$2:$E$685,I5) -> 2480740 | K5: =SUMIFS(Clean_Data!$L$2:$L$685,Clean_Data!$E$2:$E$685,I5) -> 754340 | L5: =IF(J5=0,0,K5/J5) -> 0.30407862 | M5: =J5/$J$7 -> 0.5560617
A6: 3 | B6: Mar | C6: =SUMIFS(Clean_Data!$K$2:$K$685,Clean_Data!$C$2:$C$685,A6) -> 295690 | D6: =SUMIFS(Clean_Data!$L$2:$L$685,Clean_Data!$C$2:$C$685,A6) -> 99490 | E6: =COUNTIFS(Clean_Data!$C$2:$C$685,A6) -> 49 | F6: =SUMIFS(Clean_Data!$G$2:$G$685,Clean_Data!$C$2:$C$685,A6) -> 165 | G6: =IF(C5=0,0,C6/C5-1) -> 0.12770542 | I6: Stationery | J6: =SUMIFS(Clean_Data!$K$2:$K$685,Clean_Data!$E$2:$E$685,I6) -> 660827.5 | K6: =SUMIFS(Clean_Data!$L$2:$L$685,Clean_Data!$E$2:$E$685,I6) -> 325077.5 | L6: =IF(J6=0,0,K6/J6) -> 0.4919249 | M6: =J6/$J$7 -> 0.1481255
A7: 4 | B7: Apr | C7: =SUMIFS(Clean_Data!$K$2:$K$685,Clean_Data!$C$2:$C$685,A7) -> 349867.5 | D7: =SUMIFS(Clean_Data!$L$2:$L$685,Clean_Data!$C$2:$C$685,A7) -> 117517.5 | E7: =COUNTIFS(Clean_Data!$C$2:$C$685,A7) -> 52 | F7: =SUMIFS(Clean_Data!$G$2:$G$685,Clean_Data!$C$2:$C$685,A7) -> 194 | G7: =IF(C6=0,0,C7/C6-1) -> 0.18322398 | I7: Total | J7: =SUM(J4:J6) -> 4461267.5 | K7: =SUM(K4:K6) -> 1466317.5 | L7: =K7/J7 -> 0.32867733 | M7: =SUM(M4:M6) -> 1
A8: 5 | B8: May | C8: =SUMIFS(Clean_Data!$K$2:$K$685,Clean_Data!$C$2:$C$685,A8) -> 286295 | D8: =SUMIFS(Clean_Data!$L$2:$L$685,Clean_Data!$C$2:$C$685,A8) -> 100795 | E8: =COUNTIFS(Clean_Data!$C$2:$C$685,A8) -> 55 | F8: =SUMIFS(Clean_Data!$G$2:$G$685,Clean_Data!$C$2:$C$685,A8) -> 196 | G8: =IF(C7=0,0,C8/C7-1) -> -0.1817045
A9: 6 | B9: Jun | C9: =SUMIFS(Clean_Data!$K$2:$K$685,Clean_Data!$C$2:$C$685,A9) -> 366485 | D9: =SUMIFS(Clean_Data!$L$2:$L$685,Clean_Data!$C$2:$C$685,A9) -> 124985 | E9: =COUNTIFS(Clean_Data!$C$2:$C$685,A9) -> 49 | F9: =SUMIFS(Clean_Data!$G$2:$G$685,Clean_Data!$C$2:$C$685,A9) -> 155 | G9: =IF(C8=0,0,C9/C8-1) -> 0.28009571 | I9: Region | J9: Revenue | K9: Profit | L9: Orders | M9: Share of Revenue
A10: 7 | B10: Jul | C10: =SUMIFS(Clean_Data!$K$2:$K$685,Clean_Data!$C$2:$C$685,A10) -> 372415 | D10: =SUMIFS(Clean_Data!$L$2:$L$685,Clean_Data!$C$2:$C$685,A10) -> 120815 | E10: =COUNTIFS(Clean_Data!$C$2:$C$685,A10) -> 45 | F10: =SUMIFS(Clean_Data!$G$2:$G$685,Clean_Data!$C$2:$C$685,A10) -> 178 | G10: =IF(C9=0,0,C10/C9-1) -> 0.016180744 | I10: North | J10: =SUMIFS(Clean_Data!$K$2:$K$685,Clean_Data!$D$2:$D$685,I10) -> 1066397.5 | K10: =SUMIFS(Clean_Data!$L$2:$L$685,Clean_Data!$D$2:$D$685,I10) -> 346897.5 | L10: =COUNTIFS(Clean_Data!$D$2:$D$685,I10) -> 156 | M10: =J10/$J$15 -> 0.23903465
A11: 8 | B11: Aug | C11: =SUMIFS(Clean_Data!$K$2:$K$685,Clean_Data!$C$2:$C$685,A11) -> 416837.5 | D11: =SUMIFS(Clean_Data!$L$2:$L$685,Clean_Data!$C$2:$C$685,A11) -> 133037.5 | E11: =COUNTIFS(Clean_Data!$C$2:$C$685,A11) -> 52 | F11: =SUMIFS(Clean_Data!$G$2:$G$685,Clean_Data!$C$2:$C$685,A11) -> 188 | G11: =IF(C10=0,0,C11/C10-1) -> 0.11928225 | I11: South | J11: =SUMIFS(Clean_Data!$K$2:$K$685,Clean_Data!$D$2:$D$685,I11) -> 1583167.5 | K11: =SUMIFS(Clean_Data!$L$2:$L$685,Clean_Data!$D$2:$D$685,I11) -> 514567.5 | L11: =COUNTIFS(Clean_Data!$D$2:$D$685,I11) -> 239 | M11: =J11/$J$15 -> 0.35486944
A12: 9 | B12: Sep | C12: =SUMIFS(Clean_Data!$K$2:$K$685,Clean_Data!$C$2:$C$685,A12) -> 360757.5 | D12: =SUMIFS(Clean_Data!$L$2:$L$685,Clean_Data!$C$2:$C$685,A12) -> 123307.5 | E12: =COUNTIFS(Clean_Data!$C$2:$C$685,A12) -> 60 | F12: =SUMIFS(Clean_Data!$G$2:$G$685,Clean_Data!$C$2:$C$685,A12) -> 203 | G12: =IF(C11=0,0,C12/C11-1) -> -0.13453684 | I12: East | J12: =SUMIFS(Clean_Data!$K$2:$K$685,Clean_Data!$D$2:$D$685,I12) -> 888127.5 | K12: =SUMIFS(Clean_Data!$L$2:$L$685,Clean_Data!$D$2:$D$685,I12) -> 288677.5 | L12: =COUNTIFS(Clean_Data!$D$2:$D$685,I12) -> 135 | M12: =J12/$J$15 -> 0.19907515
A13: 10 | B13: Oct | C13: =SUMIFS(Clean_Data!$K$2:$K$685,Clean_Data!$C$2:$C$685,A13) -> 422425 | D13: =SUMIFS(Clean_Data!$L$2:$L$685,Clean_Data!$C$2:$C$685,A13) -> 137325 | E13: =COUNTIFS(Clean_Data!$C$2:$C$685,A13) -> 68 | F13: =SUMIFS(Clean_Data!$G$2:$G$685,Clean_Data!$C$2:$C$685,A13) -> 221 | G13: =IF(C12=0,0,C13/C12-1) -> 0.17093893 | I13: West | J13: =SUMIFS(Clean_Data!$K$2:$K$685,Clean_Data!$D$2:$D$685,I13) -> 870945 | K13: =SUMIFS(Clean_Data!$L$2:$L$685,Clean_Data!$D$2:$D$685,I13) -> 299045 | L13: =COUNTIFS(Clean_Data!$D$2:$D$685,I13) -> 145 | M13: =J13/$J$15 -> 0.19522367
A14: 11 | B14: Nov | C14: =SUMIFS(Clean_Data!$K$2:$K$685,Clean_Data!$C$2:$C$685,A14) -> 530357.5 | D14: =SUMIFS(Clean_Data!$L$2:$L$685,Clean_Data!$C$2:$C$685,A14) -> 164107.5 | E14: =COUNTIFS(Clean_Data!$C$2:$C$685,A14) -> 81 | F14: =SUMIFS(Clean_Data!$G$2:$G$685,Clean_Data!$C$2:$C$685,A14) -> 292 | G14: =IF(C13=0,0,C14/C13-1) -> 0.25550689 | I14: Unspecified | J14: =SUMIFS(Clean_Data!$K$2:$K$685,Clean_Data!$D$2:$D$685,I14) -> 52630 | K14: =SUMIFS(Clean_Data!$L$2:$L$685,Clean_Data!$D$2:$D$685,I14) -> 17130 | L14: =COUNTIFS(Clean_Data!$D$2:$D$685,I14) -> 9 | M14: =J14/$J$15 -> 0.011797096
A15: 12 | B15: Dec | C15: =SUMIFS(Clean_Data!$K$2:$K$685,Clean_Data!$C$2:$C$685,A15) -> 486427.5 | D15: =SUMIFS(Clean_Data!$L$2:$L$685,Clean_Data!$C$2:$C$685,A15) -> 149327.5 | E15: =COUNTIFS(Clean_Data!$C$2:$C$685,A15) -> 76 | F15: =SUMIFS(Clean_Data!$G$2:$G$685,Clean_Data!$C$2:$C$685,A15) -> 255 | G15: =IF(C14=0,0,C15/C14-1) -> -0.082830921 | I15: Total | J15: =SUM(J10:J14) -> 4461267.5 | K15: =SUM(K10:K14) -> 1466317.5 | L15: =SUM(L10:L14) -> 684 | M15: =SUM(M10:M14) -> 1
B16: Total | C16: =SUM(C4:C15) -> 4461267.5 | D16: =SUM(D4:D15) -> 1466317.5 | E16: =SUM(E4:E15) -> 684 | F16: =SUM(F4:F15) -> 2396
A19: Product | B19: Category | C19: Revenue | D19: Profit | E19: Units | F19: Margin
A20: Headphones | B20: Electronics | C20: =SUMIFS(Clean_Data!$K$2:$K$685,Clean_Data!$F$2:$F$685,A20) -> 230250 | D20: =SUMIFS(Clean_Data!$L$2:$L$685,Clean_Data!$F$2:$F$685,A20) -> 76650 | E20: =SUMIFS(Clean_Data!$G$2:$G$685,Clean_Data!$F$2:$F$685,A20) -> 96 | F20: =IF(C20=0,0,D20/C20) -> 0.33289902
A21: Smart Watch | B21: Electronics | C21: =SUMIFS(Clean_Data!$K$2:$K$685,Clean_Data!$F$2:$F$685,A21) -> 590850 | D21: =SUMIFS(Clean_Data!$L$2:$L$685,Clean_Data!$F$2:$F$685,A21) -> 142050 | E21: =SUMIFS(Clean_Data!$G$2:$G$685,Clean_Data!$F$2:$F$685,A21) -> 136 | F21: =IF(C21=0,0,D21/C21) -> 0.24041635
A22: Power Bank | B22: Electronics | C22: =SUMIFS(Clean_Data!$K$2:$K$685,Clean_Data!$F$2:$F$685,A22) -> 168450 | D22: =SUMIFS(Clean_Data!$L$2:$L$685,Clean_Data!$F$2:$F$685,A22) -> 64050 | E22: =SUMIFS(Clean_Data!$G$2:$G$685,Clean_Data!$F$2:$F$685,A22) -> 116 | F22: =IF(C22=0,0,D22/C22) -> 0.38023152
A23: Bluetooth Speaker | B23: Electronics | C23: =SUMIFS(Clean_Data!$K$2:$K$685,Clean_Data!$F$2:$F$685,A23) -> 330150 | D23: =SUMIFS(Clean_Data!$L$2:$L$685,Clean_Data!$F$2:$F$685,A23) -> 104150 | E23: =SUMIFS(Clean_Data!$G$2:$G$685,Clean_Data!$F$2:$F$685,A23) -> 113 | F23: =IF(C23=0,0,D23/C23) -> 0.31546267
A24: Office Chair | B24: Furniture | C24: =SUMIFS(Clean_Data!$K$2:$K$685,Clean_Data!$F$2:$F$685,A24) -> 702800 | D24: =SUMIFS(Clean_Data!$L$2:$L$685,Clean_Data!$F$2:$F$685,A24) -> 198800 | E24: =SUMIFS(Clean_Data!$G$2:$G$685,Clean_Data!$F$2:$F$685,A24) -> 105 | F24: =IF(C24=0,0,D24/C24) -> 0.28286853
A25: Study Desk | B25: Furniture | C25: =SUMIFS(Clean_Data!$K$2:$K$685,Clean_Data!$F$2:$F$685,A25) -> 1066950 | D25: =SUMIFS(Clean_Data!$L$2:$L$685,Clean_Data!$F$2:$F$685,A25) -> 298150 | E25: =SUMIFS(Clean_Data!$G$2:$G$685,Clean_Data!$F$2:$F$685,A25) -> 124 | F25: =IF(C25=0,0,D25/C25) -> 0.2794414
A26: Bookshelf | B26: Furniture | C26: =SUMIFS(Clean_Data!$K$2:$K$685,Clean_Data!$F$2:$F$685,A26) -> 550550 | D26: =SUMIFS(Clean_Data!$L$2:$L$685,Clean_Data!$F$2:$F$685,A26) -> 179750 | E26: =SUMIFS(Clean_Data!$G$2:$G$685,Clean_Data!$F$2:$F$685,A26) -> 103 | F26: =IF(C26=0,0,D26/C26) -> 0.32649169
A27: Desk Lamp | B27: Furniture | C27: =SUMIFS(Clean_Data!$K$2:$K$685,Clean_Data!$F$2:$F$685,A27) -> 160440 | D27: =SUMIFS(Clean_Data!$L$2:$L$685,Clean_Data!$F$2:$F$685,A27) -> 77640 | E27: =SUMIFS(Clean_Data!$G$2:$G$685,Clean_Data!$F$2:$F$685,A27) -> 138 | F27: =IF(C27=0,0,D27/C27) -> 0.48391922
A28: Notebook Set | B28: Stationery | C28: =SUMIFS(Clean_Data!$K$2:$K$685,Clean_Data!$F$2:$F$685,A28) -> 134780 | D28: =SUMIFS(Clean_Data!$L$2:$L$685,Clean_Data!$F$2:$F$685,A28) -> 65180 | E28: =SUMIFS(Clean_Data!$G$2:$G$685,Clean_Data!$F$2:$F$685,A28) -> 348 | F28: =IF(C28=0,0,D28/C28) -> 0.48360291
A29: Pen Pack | B29: Stationery | C29: =SUMIFS(Clean_Data!$K$2:$K$685,Clean_Data!$F$2:$F$685,A29) -> 65687.5 | D29: =SUMIFS(Clean_Data!$L$2:$L$685,Clean_Data!$F$2:$F$685,A29) -> 38587.5 | E29: =SUMIFS(Clean_Data!$G$2:$G$685,Clean_Data!$F$2:$F$685,A29) -> 271 | F29: =IF(C29=0,0,D29/C29) -> 0.58744053
A30: Planner | B30: Stationery | C30: =SUMIFS(Clean_Data!$K$2:$K$685,Clean_Data!$F$2:$F$685,A30) -> 318810 | D30: =SUMIFS(Clean_Data!$L$2:$L$685,Clean_Data!$F$2:$F$685,A30) -> 153510 | E30: =SUMIFS(Clean_Data!$G$2:$G$685,Clean_Data!$F$2:$F$685,A30) -> 551 | F30: =IF(C30=0,0,D30/C30) -> 0.48150936
A31: Marker Set | B31: Stationery | C31: =SUMIFS(Clean_Data!$K$2:$K$685,Clean_Data!$F$2:$F$685,A31) -> 141550 | D31: =SUMIFS(Clean_Data!$L$2:$L$685,Clean_Data!$F$2:$F$685,A31) -> 67800 | E31: =SUMIFS(Clean_Data!$G$2:$G$685,Clean_Data!$F$2:$F$685,A31) -> 295 | F31: =IF(C31=0,0,D31/C31) -> 0.47898269
A32: Total | C32: =SUM(C20:C31) -> 4461267.5 | D32: =SUM(D20:D31) -> 1466317.5 | E32: =SUM(E20:E31) -> 2396 | F32: =D32/C32 -> 0.32867733

Sheet Insights
A1: Key Insights and Recommendations (based on the sample dataset)
A3: What the data shows
A4: 1. Total revenue is INR 44.6 lakh from 684 orders. Profit is INR 14.7 lakh, a margin of 32.9%.
A5: 2. Sales peak in the last quarter. Oct to Dec bring 32.3% of yearly revenue. November is the best month (INR 5.30 lakh).
A6: 3. February is the weakest month (INR 2.62 lakh). November is about twice as high.
A7: 4. Furniture earns 55.6% of revenue. Study Desk is the top product at INR 10.7 lakh.
A8: 5. Stationery gives only 14.8% of revenue but has the best margin at 49.2%.
A9: 6. Smart Watch has the lowest margin (24.0%) even though it is the third best product by revenue.
A10: 7. South is the top region with 35.5% of revenue. East and West are each near 19.5% to 19.9%.
A12: Recommendations
A13: 1. Stock up and run campaigns before October, because demand rises sharply in Q4.
A14: 2. Plan a small offer in February to lift the low month.
... A20: Percentages and totals come from the Analysis sheet. The data is a sample, so the figures are for practice, not real business decisions.
